MANIFEST.in
README.md
setup.py
collectstupid/__init__.py
collectstupid/storage.py
collectstupid.egg-info/PKG-INFO
collectstupid.egg-info/SOURCES.txt
collectstupid.egg-info/dependency_links.txt
collectstupid.egg-info/requires.txt
collectstupid.egg-info/top_level.txt
collectstupid/management/__init__.py
collectstupid/management/commands/__init__.py
collectstupid/management/commands/collectstupid.py