Metadata-Version: 1.1
Name: collectstupid
Version: 15.11.4
Summary: A Faster Collect Static (sometimes) for Django
Home-page: https://github.com/pizzapanther/collectstupid
Author: Paul Bailey
Author-email: paul.m.bailey@gmail.com
License: MIT
Platform: UNKNOWN
Classifier: Programming Language :: Python :: 2.7
Classifier: Programming Language :: Python :: 3
